nonebot_plugin_fun_content/__init__.py
nonebot_plugin_fun_content/api.py
nonebot_plugin_fun_content/config.py
nonebot_plugin_fun_content/data/fun_content.db
nonebot_plugin_fun_content/database.py
nonebot_plugin_fun_content/handlers.py
nonebot_plugin_fun_content/response_handler.py
nonebot_plugin_fun_content/scheduler.py
nonebot_plugin_fun_content/utils.py
nonebot_plugin_fun_content-0.4.0.dist-info/LICENSE
nonebot_plugin_fun_content-0.4.0.dist-info/METADATA
nonebot_plugin_fun_content-0.4.0.dist-info/WHEEL
nonebot_plugin_fun_content-0.4.0.dist-info/RECORD
