Metadata-Version: 2.3
Name: nonebot-plugin-fun-content
Version: 0.4.0
Summary: 从本地数据库或在线API获取趣味内容，如一言、土味情话、舔狗日记等。可以分群开关功能，支持定时任务。
License: MIT
Author: Endless-Path
Author-email: rk.chensiyu@gmail.com
Requires-Python: >=3.10,<4.0
Classifier: License :: OSI Approved :: MIT License
Classifier: Programming Language :: Python :: 3
Classifier: Programming Language :: Python :: 3.10
Classifier: Programming Language :: Python :: 3.11
Classifier: Programming Language :: Python :: 3.12
Classifier: Programming Language :: Python :: 3.13
Requires-Dist: aiosqlite (>=0.19.0,<0.20.0)
Requires-Dist: httpx (>=0.26.0,<0.27.0)
Requires-Dist: nonebot-adapter-onebot (>=2.4.1,<3.0.0)
Requires-Dist: nonebot-plugin-apscheduler (>=0.4.0,<0.5.0)
Requires-Dist: nonebot2 (>=2.2.1,<3.0.0)
Requires-Dist: pydantic (>=1.10.13,<2.0.0)
